{"_ts":[1498907336],"_r":{"breakdown":{"html":{"bytes":[17772],"requests":[1]},"js":{"bytes":[674636],"requests":[20]},"css":{"bytes":[415687],"requests":[23]},"image":{"bytes":[10192711],"requests":[38]},"flash":{"bytes":[0],"requests":[0]},"font":{"bytes":[452610],"requests":[12]},"other":{"bytes":[0],"requests":[0]}},"date":[1498907336],"domElements":[685],"domInteractive":[16817],"firstPaint":[2184],"fullyLoaded":[20759],"id":["170701_A3_HRK"],"loadTime":[20606],"render":[2675],"SpeedIndex":[16513],"TTFB":[234],"videoFrames":[[{"_i":"frame_0000.jpg","_t":0,"_vc":0},{"_i":"frame_0027.jpg","_t":2700,"_vc":20},{"_i":"frame_0028.jpg","_t":2800,"_vc":20},{"_i":"frame_0030.jpg","_t":3000,"_vc":21},{"_i":"frame_0031.jpg","_t":3100,"_vc":21},{"_i":"frame_0034.jpg","_t":3400,"_vc":17},{"_i":"frame_0035.jpg","_t":3500,"_vc":17},{"_i":"frame_0180.jpg","_t":18000,"_vc":18},{"_i":"frame_0182.jpg","_t":18200,"_vc":17},{"_i":"frame_0185.jpg","_t":18500,"_vc":18},{"_i":"frame_0186.jpg","_t":18600,"_vc":18},{"_i":"frame_0187.jpg","_t":18700,"_vc":18},{"_i":"frame_0188.jpg","_t":18800,"_vc":17},{"_i":"frame_0191.jpg","_t":19100,"_vc":23},{"_i":"frame_0192.jpg","_t":19200,"_vc":50},{"_i":"frame_0193.jpg","_t":19300,"_vc":59},{"_i":"frame_0195.jpg","_t":19500,"_vc":90},{"_i":"frame_0197.jpg","_t":19700,"_vc":99},{"_i":"frame_0198.jpg","_t":19800,"_vc":99},{"_i":"frame_0199.jpg","_t":19900,"_vc":100}]],"visualComplete":[19900],"lighthouse":[null],"pagespeed":[3]}}