{"_ts":[1561946915],"_r":{"breakdown":{"html":{"bytes":[9993],"requests":[3]},"js":{"bytes":[248648],"requests":[8]},"css":{"bytes":[45161],"requests":[6]},"image":{"bytes":[6736042],"requests":[16]},"flash":{"bytes":[0],"requests":[0]},"font":{"bytes":[233279],"requests":[11]},"video":{"bytes":[2015178],"requests":[1]},"other":{"bytes":[0],"requests":[0]}},"date":[1561946915],"domElements":[686],"domInteractive":[2535],"firstPaint":[1319.859999996],"fullyLoaded":[16302],"id":["190701_EX_11f024fe710894954cd6f125877f81ec"],"loadTime":[13392],"render":[1400],"SpeedIndex":[5141],"TTFB":[383],"videoFrames":[[{"_i":"ms_000000.jpg","_t":0,"_vc":0},{"_i":"ms_001400.jpg","_t":1400,"_vc":4},{"_i":"ms_001500.jpg","_t":1500,"_vc":6},{"_i":"ms_001600.jpg","_t":1600,"_vc":8},{"_i":"ms_001700.jpg","_t":1700,"_vc":8},{"_i":"ms_001800.jpg","_t":1800,"_vc":9},{"_i":"ms_001900.jpg","_t":1900,"_vc":9},{"_i":"ms_002000.jpg","_t":2000,"_vc":9},{"_i":"ms_002600.jpg","_t":2600,"_vc":37},{"_i":"ms_002800.jpg","_t":2800,"_vc":90},{"_i":"ms_003400.jpg","_t":3400,"_vc":91},{"_i":"ms_003600.jpg","_t":3600,"_vc":91},{"_i":"ms_004500.jpg","_t":4500,"_vc":91},{"_i":"ms_004800.jpg","_t":4800,"_vc":92},{"_i":"ms_004900.jpg","_t":4900,"_vc":92},{"_i":"ms_011900.jpg","_t":11900,"_vc":46},{"_i":"ms_014100.jpg","_t":14100,"_vc":46},{"_i":"ms_014200.jpg","_t":14200,"_vc":46},{"_i":"ms_014300.jpg","_t":14300,"_vc":46},{"_i":"ms_014400.jpg","_t":14400,"_vc":51},{"_i":"ms_014500.jpg","_t":14500,"_vc":56},{"_i":"ms_014600.jpg","_t":14600,"_vc":57},{"_i":"ms_014700.jpg","_t":14700,"_vc":58},{"_i":"ms_014800.jpg","_t":14800,"_vc":58},{"_i":"ms_014900.jpg","_t":14900,"_vc":59},{"_i":"ms_015000.jpg","_t":15000,"_vc":62},{"_i":"ms_015100.jpg","_t":15100,"_vc":62},{"_i":"ms_015200.jpg","_t":15200,"_vc":72},{"_i":"ms_015301.jpg","_t":15301,"_vc":72},{"_i":"ms_015400.jpg","_t":15400,"_vc":96},{"_i":"ms_015500.jpg","_t":15500,"_vc":96},{"_i":"ms_015600.jpg","_t":15600,"_vc":99},{"_i":"ms_015700.jpg","_t":15700,"_vc":99},{"_i":"ms_015800.jpg","_t":15800,"_vc":98},{"_i":"ms_015900.jpg","_t":15900,"_vc":98},{"_i":"ms_016000.jpg","_t":16000,"_vc":99},{"_i":"ms_016100.jpg","_t":16100,"_vc":99},{"_i":"ms_016200.jpg","_t":16200,"_vc":100},{"_i":"ms_016300.jpg","_t":16300,"_vc":100}]],"visualComplete":[16200],"lighthouse":[19],"pagespeed":[26]}}